[
  {
    "id": "mon_bear_thorn",
    "type": "MONSTER",
    "copy-from": "mon_bear",
    "name": "thorn-bear",
    "description": "A bear changed by the power of the forest.  Its eyes are a brilliant green, moss grows throughout its thick fur, and foot-long woody thorns sprout from its body.",
    "default_faction": "forest_elemental_faction",
    "melee_skill": 7,
    "armor": { "bash": 10, "cut": 8 },
    "aggression": -10,
    "morale": 200,
    "harvest": "harvest_thornbear",
    "special_attacks": [
      {
        "type": "bite",
        "cooldown": 10,
        "damage_max_instance": [ { "damage_type": "stab", "amount": 12, "armor_penetration": 8 } ]
      }
    ],
    "anger_triggers": [ "HOSTILE_SEEN", "HURT", "PLAYER_CLOSE" ],
    "flags": [ "SEES", "HEARS", "SMELLS", "ANIMAL", "WARM", "BASHES", "PUSH_MON", "PATH_AVOID_FIRE", "PRIORITIZE_TARGETS" ]
  },
  {
    "id": "mon_owl_shadow_lilitu",
    "type": "MONSTER",
    "name": { "str": "lilitu", "str_pl": "lilitu" },
    "description": "An owl, but one with a body the size of a child.  Then you notice that it has human fingers at its wing joint and human hands instead of an owl's talons.  Its black feathers seem to absorb all light.",
    "bodytype": "bird",
    "default_faction": "shadow_elemental_faction",
    "species": [ "SHADOW_ELEMENTAL" ],
    "volume": "35000 ml",
    "weight": "40000 g",
    "hp": 35,
    "speed": 70,
    "material": [ "flesh" ],
    "symbol": "s",
    "color": "dark_gray",
    "aggression": 0,
    "morale": 105,
    "melee_skill": 4,
    "melee_dice": 1,
    "melee_dice_sides": 6,
    "//": "low damage because it doesn't have talons",
    "dodge": 5,
    "armor": { "bash": 5, "cut": 5, "stab": 5, "electricity": 15 },
    "vision_day": 15,
    "vision_night": 25,
    "families": [ "prof_intro_biology", "prof_wp_basic_bird" ],
    "weakpoint_sets": [ "wps_bird_body" ],
    "harvest": "harvest_lilitu",
    "special_attacks": [
      {
        "type": "bite",
        "cooldown": 15,
        "damage_max_instance": [ { "damage_type": "stab", "amount": 10, "armor_penetration": 8 } ]
      },
      {
        "type": "leap",
        "cooldown": 10,
        "move_cost": 50,
        "allow_no_target": true,
        "max_range": 5,
        "message": "With a burst of its wings, %1$s hurtles through the air!"
      },
      {
        "id": "lilitu_disease",
        "type": "spell",
        "spell_data": { "id": "lilitu_disease_spell", "min_level": 3 },
        "cooldown": 25,
        "monster_message": "%1$s beats its wings and a rank wind blows around you!"
      }
    ],
    "fear_triggers": [ "FIRE" ],
    "anger_triggers": [ "HOSTILE_SEEN", "HURT", "STALK", "PLAYER_CLOSE" ],
    "flags": [ "SEES", "HEARS", "SMELLS", "PATH_AVOID_DANGER_1", "STUMBLES", "FLIES", "WARM", "NIGHT_INVISIBILITY", "HIT_AND_RUN" ]
  }
]
